minify_html_core-0.8.1.dist-info/METADATA
minify_html_core-0.8.1.dist-info/WHEEL
minify_html_core/__init__.py
minify_html_core/minify_html_core.cpython-38-darwin.so
minify_html_core-0.8.1.dist-info/RECORD
