Metadata-Version: 2.1
Name: minify_html_core
Version: 0.8.1
Summary: Extremely fast and smart HTML minifier
Home-Page: https://github.com/wilsonzlin/minify-html
Author: Wilson Lin <code@wilsonl.in>
Author-email: Wilson Lin <code@wilsonl.in>
License: MIT
Project-URL: Source Code, https://github.com/wilsonzlin/minify-html.git
